{
  "id": "foundry-v2-telemetry_first_execution-20260605_103839",
  "enabled": true,
  "action": "telemetry_first_execution",
  "reason": "JasonOS Foundry ceiling-mode concurrent lane: telemetry_first_execution. Promotion gates are execution gates only.",
  "status": "queued",
  "created_at": "2026-06-05 10:38:39",
  "expires_utc": "2026-06-05T22:38:39Z",
  "jason_intervention": "only_key_decisions_or_true_blockers",
  "published_at": "2026-06-05 10:38:39",
  "published_at_utc": "2026-06-05T10:38:39Z"
}