{
  "component": "scarflix_v2_streaming_layered_validator",
  "updated_utc": "2026-06-19T04:30:32Z",
  "status": "RUNNING",
  "qa_component": "scarflix_v2_materialized_plex_decision_qa_node",
  "decision_probe_skip": 0,
  "decision_probe_limit": 0,
  "range_bytes": 4194304,
  "summary": {
    "total": 66,
    "passed": 59,
    "review": 7,
    "reasons": {
      "webdav_head_and_temporary_range_warm_passed": 57,
      "webdav_head_fallback_range_and_temporary_range_warm_passed": 2,
      "webdav_head_upstream_server_error": 4,
      "webdav_head_timeout": 3
    }
  },
  "recent_results": [
    {
      "component": "scarflix_v2_streaming_layered_validator",
      "updated_utc": "2026-06-19T04:27:26Z",
      "target_hash": "ScarFLIX_part-02ca4b68340aafa1",
      "target_link": "D:\\StremioCatalog\\_Hybrid\\Movies\\_ScarFLIXLive\\06 Discover Movies\\Idiocracy (2006)\\ScarFLIX_part-02ca4b68340aafa1",
      "webdav_url": "http://127.0.0.1:18789/media/ScarFLIX_part-02ca4b68340aafa1/stream.mkv",
      "map_loaded": true,
      "map_generated_utc": "2026-06-19T04:01:19Z",
      "map_entry_found": true,
      "temporary_buffering": {
        "enabled": true,
        "persisted": false,
        "range_bytes_requested": 4194304
      },
      "layers": {
        "local_symlink_metadata": {
          "status": "PASS",
          "link": "D:\\StremioCatalog\\_Hybrid\\Movies\\_ScarFLIXLive\\06 Discover Movies\\Idiocracy (2006)\\ScarFLIX_part-02ca4b68340aafa1",
          "stream_path": "D:\\StremioCatalog\\_Hybrid\\Movies\\_ScarFLIXLive\\06 Discover Movies\\Idiocracy (2006)\\ScarFLIX_part-02ca4b68340aafa1",
          "is_symbolic_link": true,
          "link_target": "S:\\media\\ScarFLIX_part-02ca4b68340aafa1",
          "error": "",
          "blocking": false,
          "exists": true,
          "is_directory": false,
          "is_file": false
        },
        "webdav_head": {
          "ok": true,
          "method": "HEAD",
          "url": "http://127.0.0.1:18789/media/ScarFLIX_part-02ca4b68340aafa1/stream.mkv",
          "status_code": 200,
          "bytes_read": 0,
          "content_length": "578065188",
          "content_type": "application/octet-stream",
          "accept_ranges": "bytes",
          "elapsed_ms": 2250,
          "attempt": 1,
          "reason": "ok",
          "attempts": 1
        },
        "webdav_head_attempts": [
          {
            "ok": true,
            "method": "HEAD",
            "url": "http://127.0.0.1:18789/media/ScarFLIX_part-02ca4b68340aafa1/stream.mkv",
            "status_code": 200,
            "bytes_read": 0,
            "content_length": "578065188",
            "content_type": "application/octet-stream",
            "accept_ranges": "bytes",
            "elapsed_ms": 2250,
            "attempt": 1,
            "reason": "ok"
          }
        ],
        "webdav_range_warm": {
          "ok": true,
          "method": "GET",
          "url": "http://127.0.0.1:18789/media/ScarFLIX_part-02ca4b68340aafa1/stream.mkv",
          "status_code": 206,
          "bytes_read": 4194304,
          "content_length": "4194304",
          "content_type": "application/octet-stream",
          "accept_ranges": "bytes",
          "elapsed_ms": 4190,
          "reason": "ok"
        }
      },
      "status": "PASS",
      "reason": "webdav_head_and_temporary_range_warm_passed",
      "elapsed_ms": 6441
    },
    {
      "component": "scarflix_v2_streaming_layered_validator",
      "updated_utc": "2026-06-19T04:27:36Z",
      "target_hash": "ScarFLIX_part-b6f5180a4a7d0823",
      "target_link": "D:\\StremioCatalog\\_Hybrid\\Movies\\_ScarFLIXLive\\06 Discover Movies\\Ikiru (1952)\\ScarFLIX_part-b6f5180a4a7d0823",
      "webdav_url": "http://127.0.0.1:18789/media/ScarFLIX_part-b6f5180a4a7d0823/stream.mkv",
      "map_loaded": true,
      "map_generated_utc": "2026-06-19T04:01:19Z",
      "map_entry_found": true,
      "temporary_buffering": {
        "enabled": true,
        "persisted": false,
        "range_bytes_requested": 4194304
      },
      "layers": {
        "local_symlink_metadata": {
          "status": "PASS",
          "link": "D:\\StremioCatalog\\_Hybrid\\Movies\\_ScarFLIXLive\\06 Discover Movies\\Ikiru (1952)\\ScarFLIX_part-b6f5180a4a7d0823",
          "stream_path": "D:\\StremioCatalog\\_Hybrid\\Movies\\_ScarFLIXLive\\06 Discover Movies\\Ikiru (1952)\\ScarFLIX_part-b6f5180a4a7d0823",
          "is_symbolic_link": true,
          "link_target": "S:\\media\\ScarFLIX_part-b6f5180a4a7d0823",
          "error": "",
          "blocking": false,
          "exists": true,
          "is_directory": false,
          "is_file": false
        },
        "webdav_head": {
          "ok": true,
          "method": "HEAD",
          "url": "http://127.0.0.1:18789/media/ScarFLIX_part-b6f5180a4a7d0823/stream.mkv",
          "status_code": 200,
          "bytes_read": 0,
          "content_length": "2930059094",
          "content_type": "application/octet-stream",
          "accept_ranges": "bytes",
          "elapsed_ms": 1610,
          "attempt": 1,
          "reason": "ok",
          "attempts": 1
        },
        "webdav_head_attempts": [
          {
            "ok": true,
            "method": "HEAD",
            "url": "http://127.0.0.1:18789/media/ScarFLIX_part-b6f5180a4a7d0823/stream.mkv",
            "status_code": 200,
            "bytes_read": 0,
            "content_length": "2930059094",
            "content_type": "application/octet-stream",
            "accept_ranges": "bytes",
            "elapsed_ms": 1610,
            "attempt": 1,
            "reason": "ok"
          }
        ],
        "webdav_range_warm": {
          "ok": true,
          "method": "GET",
          "url": "http://127.0.0.1:18789/media/ScarFLIX_part-b6f5180a4a7d0823/stream.mkv",
          "status_code": 206,
          "bytes_read": 4194304,
          "content_length": "4194304",
          "content_type": "application/octet-stream",
          "accept_ranges": "bytes",
          "elapsed_ms": 3601,
          "reason": "ok"
        }
      },
      "status": "PASS",
      "reason": "webdav_head_and_temporary_range_warm_passed",
      "elapsed_ms": 5213
    },
    {
      "component": "scarflix_v2_streaming_layered_validator",
      "updated_utc": "2026-06-19T04:28:05Z",
      "target_hash": "ScarFLIX_part-1ce460822ca1239a",
      "target_link": "D:\\StremioCatalog\\_Hybrid\\Movies\\_ScarFLIXLive\\06 Discover Movies\\In the Mood for Love (2000)\\ScarFLIX_part-1ce460822ca1239a",
      "webdav_url": "http://127.0.0.1:18789/media/ScarFLIX_part-1ce460822ca1239a/stream.mkv",
      "map_loaded": true,
      "map_generated_utc": "2026-06-19T04:01:19Z",
      "map_entry_found": true,
      "temporary_buffering": {
        "enabled": true,
        "persisted": false,
        "range_bytes_requested": 4194304
      },
      "layers": {
        "local_symlink_metadata": {
          "status": "PASS",
          "link": "D:\\StremioCatalog\\_Hybrid\\Movies\\_ScarFLIXLive\\06 Discover Movies\\In the Mood for Love (2000)\\ScarFLIX_part-1ce460822ca1239a",
          "stream_path": "D:\\StremioCatalog\\_Hybrid\\Movies\\_ScarFLIXLive\\06 Discover Movies\\In the Mood for Love (2000)\\ScarFLIX_part-1ce460822ca1239a",
          "is_symbolic_link": true,
          "link_target": "S:\\media\\ScarFLIX_part-1ce460822ca1239a",
          "error": "",
          "blocking": false,
          "exists": true,
          "is_directory": false,
          "is_file": false
        },
        "webdav_head": {
          "ok": true,
          "method": "HEAD",
          "url": "http://127.0.0.1:18789/media/ScarFLIX_part-1ce460822ca1239a/stream.mkv",
          "status_code": 200,
          "bytes_read": 0,
          "content_length": "4595111572",
          "content_type": "application/octet-stream",
          "accept_ranges": "bytes",
          "elapsed_ms": 1763,
          "attempt": 1,
          "reason": "ok",
          "attempts": 1
        },
        "webdav_head_attempts": [
          {
            "ok": true,
            "method": "HEAD",
            "url": "http://127.0.0.1:18789/media/ScarFLIX_part-1ce460822ca1239a/stream.mkv",
            "status_code": 200,
            "bytes_read": 0,
            "content_length": "4595111572",
            "content_type": "application/octet-stream",
            "accept_ranges": "bytes",
            "elapsed_ms": 1763,
            "attempt": 1,
            "reason": "ok"
          }
        ],
        "webdav_range_warm": {
          "ok": true,
          "method": "GET",
          "url": "http://127.0.0.1:18789/media/ScarFLIX_part-1ce460822ca1239a/stream.mkv",
          "status_code": 206,
          "bytes_read": 4194304,
          "content_length": "4194304",
          "content_type": "application/octet-stream",
          "accept_ranges": "bytes",
          "elapsed_ms": 3961,
          "reason": "ok"
        }
      },
      "status": "PASS",
      "reason": "webdav_head_and_temporary_range_warm_passed",
      "elapsed_ms": 5725
    },
    {
      "component": "scarflix_v2_streaming_layered_validator",
      "updated_utc": "2026-06-19T04:28:37Z",
      "target_hash": "ScarFLIX_part-52c63b31fc203627",
      "target_link": "D:\\StremioCatalog\\_Hybrid\\Movies\\_ScarFLIXLive\\06 Discover Movies\\Indecent Proposal (1993)\\ScarFLIX_part-52c63b31fc203627",
      "webdav_url": "http://127.0.0.1:18789/media/ScarFLIX_part-52c63b31fc203627/stream.mkv",
      "map_loaded": true,
      "map_generated_utc": "2026-06-19T04:01:19Z",
      "map_entry_found": true,
      "temporary_buffering": {
        "enabled": true,
        "persisted": false,
        "range_bytes_requested": 4194304
      },
      "layers": {
        "local_symlink_metadata": {
          "status": "PASS",
          "link": "D:\\StremioCatalog\\_Hybrid\\Movies\\_ScarFLIXLive\\06 Discover Movies\\Indecent Proposal (1993)\\ScarFLIX_part-52c63b31fc203627",
          "stream_path": "D:\\StremioCatalog\\_Hybrid\\Movies\\_ScarFLIXLive\\06 Discover Movies\\Indecent Proposal (1993)\\ScarFLIX_part-52c63b31fc203627",
          "is_symbolic_link": true,
          "link_target": "S:\\media\\ScarFLIX_part-52c63b31fc203627",
          "error": "",
          "blocking": false,
          "exists": true,
          "is_directory": false,
          "is_file": false
        },
        "webdav_head": {
          "ok": true,
          "method": "HEAD",
          "url": "http://127.0.0.1:18789/media/ScarFLIX_part-52c63b31fc203627/stream.mkv",
          "status_code": 200,
          "bytes_read": 0,
          "content_length": "966837947",
          "content_type": "application/octet-stream",
          "accept_ranges": "bytes",
          "elapsed_ms": 1489,
          "attempt": 1,
          "reason": "ok",
          "attempts": 1
        },
        "webdav_head_attempts": [
          {
            "ok": true,
            "method": "HEAD",
            "url": "http://127.0.0.1:18789/media/ScarFLIX_part-52c63b31fc203627/stream.mkv",
            "status_code": 200,
            "bytes_read": 0,
            "content_length": "966837947",
            "content_type": "application/octet-stream",
            "accept_ranges": "bytes",
            "elapsed_ms": 1489,
            "attempt": 1,
            "reason": "ok"
          }
        ],
        "webdav_range_warm": {
          "ok": true,
          "method": "GET",
          "url": "http://127.0.0.1:18789/media/ScarFLIX_part-52c63b31fc203627/stream.mkv",
          "status_code": 206,
          "bytes_read": 4194304,
          "content_length": "4194304",
          "content_type": "application/octet-stream",
          "accept_ranges": "bytes",
          "elapsed_ms": 4334,
          "reason": "ok"
        }
      },
      "status": "PASS",
      "reason": "webdav_head_and_temporary_range_warm_passed",
      "elapsed_ms": 5824
    },
    {
      "component": "scarflix_v2_streaming_layered_validator",
      "updated_utc": "2026-06-19T04:29:04Z",
      "target_hash": "ScarFLIX_part-076bee16088c0032",
      "target_link": "D:\\StremioCatalog\\_Hybrid\\Movies\\_ScarFLIXLive\\06 Discover Movies\\Josee, the Tiger and the Fish (2020)\\ScarFLIX_part-076bee16088c0032",
      "webdav_url": "http://127.0.0.1:18789/media/ScarFLIX_part-076bee16088c0032/stream.mkv",
      "map_loaded": true,
      "map_generated_utc": "2026-06-19T04:01:19Z",
      "map_entry_found": true,
      "temporary_buffering": {
        "enabled": true,
        "persisted": false,
        "range_bytes_requested": 4194304
      },
      "layers": {
        "local_symlink_metadata": {
          "status": "PASS",
          "link": "D:\\StremioCatalog\\_Hybrid\\Movies\\_ScarFLIXLive\\06 Discover Movies\\Josee, the Tiger and the Fish (2020)\\ScarFLIX_part-076bee16088c0032",
          "stream_path": "D:\\StremioCatalog\\_Hybrid\\Movies\\_ScarFLIXLive\\06 Discover Movies\\Josee, the Tiger and the Fish (2020)\\ScarFLIX_part-076bee16088c0032",
          "is_symbolic_link": true,
          "link_target": "S:\\media\\ScarFLIX_part-076bee16088c0032",
          "error": "",
          "blocking": false,
          "exists": true,
          "is_directory": false,
          "is_file": false
        },
        "webdav_head": {
          "ok": true,
          "method": "HEAD",
          "url": "http://127.0.0.1:18789/media/ScarFLIX_part-076bee16088c0032/stream.mkv",
          "status_code": 200,
          "bytes_read": 0,
          "content_length": "1096161214",
          "content_type": "application/octet-stream",
          "accept_ranges": "bytes",
          "elapsed_ms": 1893,
          "attempt": 1,
          "reason": "ok",
          "attempts": 1
        },
        "webdav_head_attempts": [
          {
            "ok": true,
            "method": "HEAD",
            "url": "http://127.0.0.1:18789/media/ScarFLIX_part-076bee16088c0032/stream.mkv",
            "status_code": 200,
            "bytes_read": 0,
            "content_length": "1096161214",
            "content_type": "application/octet-stream",
            "accept_ranges": "bytes",
            "elapsed_ms": 1893,
            "attempt": 1,
            "reason": "ok"
          }
        ],
        "webdav_range_warm": {
          "ok": true,
          "method": "GET",
          "url": "http://127.0.0.1:18789/media/ScarFLIX_part-076bee16088c0032/stream.mkv",
          "status_code": 206,
          "bytes_read": 4194304,
          "content_length": "4194304",
          "content_type": "application/octet-stream",
          "accept_ranges": "bytes",
          "elapsed_ms": 3563,
          "reason": "ok"
        }
      },
      "status": "PASS",
      "reason": "webdav_head_and_temporary_range_warm_passed",
      "elapsed_ms": 5457
    },
    {
      "component": "scarflix_v2_streaming_layered_validator",
      "updated_utc": "2026-06-19T04:29:35Z",
      "target_hash": "ScarFLIX_part-c624488ce1ac323e",
      "target_link": "D:\\StremioCatalog\\_Hybrid\\Movies\\_ScarFLIXLive\\06 Discover Movies\\L.E.T.H.A.L. Ladies Return to Savage Beach (1998)\\ScarFLIX_part-c624488ce1ac323e",
      "webdav_url": "http://127.0.0.1:18789/media/ScarFLIX_part-c624488ce1ac323e/stream.mkv",
      "map_loaded": true,
      "map_generated_utc": "2026-06-19T04:01:19Z",
      "map_entry_found": true,
      "temporary_buffering": {
        "enabled": true,
        "persisted": false,
        "range_bytes_requested": 4194304
      },
      "layers": {
        "local_symlink_metadata": {
          "status": "PASS",
          "link": "D:\\StremioCatalog\\_Hybrid\\Movies\\_ScarFLIXLive\\06 Discover Movies\\L.E.T.H.A.L. Ladies Return to Savage Beach (1998)\\ScarFLIX_part-c624488ce1ac323e",
          "stream_path": "D:\\StremioCatalog\\_Hybrid\\Movies\\_ScarFLIXLive\\06 Discover Movies\\L.E.T.H.A.L. Ladies Return to Savage Beach (1998)\\ScarFLIX_part-c624488ce1ac323e",
          "is_symbolic_link": true,
          "link_target": "S:\\media\\ScarFLIX_part-c624488ce1ac323e",
          "error": "",
          "blocking": false,
          "exists": true,
          "is_directory": false,
          "is_file": false
        },
        "webdav_head": {
          "ok": true,
          "method": "HEAD",
          "url": "http://127.0.0.1:18789/media/ScarFLIX_part-c624488ce1ac323e/stream.mkv",
          "status_code": 200,
          "bytes_read": 0,
          "content_length": "4507146603",
          "content_type": "application/octet-stream",
          "accept_ranges": "bytes",
          "elapsed_ms": 1730,
          "attempt": 1,
          "reason": "ok",
          "attempts": 1
        },
        "webdav_head_attempts": [
          {
            "ok": true,
            "method": "HEAD",
            "url": "http://127.0.0.1:18789/media/ScarFLIX_part-c624488ce1ac323e/stream.mkv",
            "status_code": 200,
            "bytes_read": 0,
            "content_length": "4507146603",
            "content_type": "application/octet-stream",
            "accept_ranges": "bytes",
            "elapsed_ms": 1730,
            "attempt": 1,
            "reason": "ok"
          }
        ],
        "webdav_range_warm": {
          "ok": true,
          "method": "GET",
          "url": "http://127.0.0.1:18789/media/ScarFLIX_part-c624488ce1ac323e/stream.mkv",
          "status_code": 206,
          "bytes_read": 4194304,
          "content_length": "4194304",
          "content_type": "application/octet-stream",
          "accept_ranges": "bytes",
          "elapsed_ms": 3720,
          "reason": "ok"
        }
      },
      "status": "PASS",
      "reason": "webdav_head_and_temporary_range_warm_passed",
      "elapsed_ms": 5451
    },
    {
      "component": "scarflix_v2_streaming_layered_validator",
      "updated_utc": "2026-06-19T04:29:41Z",
      "target_hash": "ScarFLIX_part-a6694a54be2d1ec9",
      "target_link": "D:\\StremioCatalog\\_Hybrid\\Movies\\_ScarFLIXLive\\06 Discover Movies\\Legend (2015)\\ScarFLIX_part-a6694a54be2d1ec9",
      "webdav_url": "http://127.0.0.1:18789/media/ScarFLIX_part-a6694a54be2d1ec9/stream.mkv",
      "map_loaded": true,
      "map_generated_utc": "2026-06-19T04:01:19Z",
      "map_entry_found": true,
      "temporary_buffering": {
        "enabled": true,
        "persisted": false,
        "range_bytes_requested": 4194304
      },
      "layers": {
        "local_symlink_metadata": {
          "status": "PASS",
          "link": "D:\\StremioCatalog\\_Hybrid\\Movies\\_ScarFLIXLive\\06 Discover Movies\\Legend (2015)\\ScarFLIX_part-a6694a54be2d1ec9",
          "stream_path": "D:\\StremioCatalog\\_Hybrid\\Movies\\_ScarFLIXLive\\06 Discover Movies\\Legend (2015)\\ScarFLIX_part-a6694a54be2d1ec9",
          "is_symbolic_link": true,
          "link_target": "S:\\media\\ScarFLIX_part-a6694a54be2d1ec9",
          "error": "",
          "blocking": false,
          "exists": true,
          "is_directory": false,
          "is_file": false
        },
        "webdav_head": {
          "ok": true,
          "method": "HEAD",
          "url": "http://127.0.0.1:18789/media/ScarFLIX_part-a6694a54be2d1ec9/stream.mkv",
          "status_code": 200,
          "bytes_read": 0,
          "content_length": "2062264521",
          "content_type": "application/octet-stream",
          "accept_ranges": "bytes",
          "elapsed_ms": 1573,
          "attempt": 1,
          "reason": "ok",
          "attempts": 1
        },
        "webdav_head_attempts": [
          {
            "ok": true,
            "method": "HEAD",
            "url": "http://127.0.0.1:18789/media/ScarFLIX_part-a6694a54be2d1ec9/stream.mkv",
            "status_code": 200,
            "bytes_read": 0,
            "content_length": "2062264521",
            "content_type": "application/octet-stream",
            "accept_ranges": "bytes",
            "elapsed_ms": 1573,
            "attempt": 1,
            "reason": "ok"
          }
        ],
        "webdav_range_warm": {
          "ok": true,
          "method": "GET",
          "url": "http://127.0.0.1:18789/media/ScarFLIX_part-a6694a54be2d1ec9/stream.mkv",
          "status_code": 206,
          "bytes_read": 4194304,
          "content_length": "4194304",
          "content_type": "application/octet-stream",
          "accept_ranges": "bytes",
          "elapsed_ms": 4332,
          "reason": "ok"
        }
      },
      "status": "PASS",
      "reason": "webdav_head_and_temporary_range_warm_passed",
      "elapsed_ms": 5906
    },
    {
      "component": "scarflix_v2_streaming_layered_validator",
      "updated_utc": "2026-06-19T04:29:53Z",
      "target_hash": "ScarFLIX_part-0d465a7414c7c73a",
      "target_link": "D:\\StremioCatalog\\_Hybrid\\Movies\\_ScarFLIXLive\\06 Discover Movies\\Legends of the Fall (1994)\\ScarFLIX_part-0d465a7414c7c73a",
      "webdav_url": "http://127.0.0.1:18789/media/ScarFLIX_part-0d465a7414c7c73a/stream.mkv",
      "map_loaded": true,
      "map_generated_utc": "2026-06-19T04:01:19Z",
      "map_entry_found": true,
      "temporary_buffering": {
        "enabled": true,
        "persisted": false,
        "range_bytes_requested": 4194304
      },
      "layers": {
        "local_symlink_metadata": {
          "status": "PASS",
          "link": "D:\\StremioCatalog\\_Hybrid\\Movies\\_ScarFLIXLive\\06 Discover Movies\\Legends of the Fall (1994)\\ScarFLIX_part-0d465a7414c7c73a",
          "stream_path": "D:\\StremioCatalog\\_Hybrid\\Movies\\_ScarFLIXLive\\06 Discover Movies\\Legends of the Fall (1994)\\ScarFLIX_part-0d465a7414c7c73a",
          "is_symbolic_link": true,
          "link_target": "S:\\media\\ScarFLIX_part-0d465a7414c7c73a",
          "error": "",
          "blocking": false,
          "exists": true,
          "is_directory": false,
          "is_file": false
        },
        "webdav_head": {
          "ok": true,
          "method": "HEAD",
          "url": "http://127.0.0.1:18789/media/ScarFLIX_part-0d465a7414c7c73a/stream.mkv",
          "status_code": 200,
          "bytes_read": 0,
          "content_length": "1982767471",
          "content_type": "application/octet-stream",
          "accept_ranges": "bytes",
          "elapsed_ms": 1213,
          "attempt": 1,
          "reason": "ok",
          "attempts": 1
        },
        "webdav_head_attempts": [
          {
            "ok": true,
            "method": "HEAD",
            "url": "http://127.0.0.1:18789/media/ScarFLIX_part-0d465a7414c7c73a/stream.mkv",
            "status_code": 200,
            "bytes_read": 0,
            "content_length": "1982767471",
            "content_type": "application/octet-stream",
            "accept_ranges": "bytes",
            "elapsed_ms": 1213,
            "attempt": 1,
            "reason": "ok"
          }
        ],
        "webdav_range_warm": {
          "ok": true,
          "method": "GET",
          "url": "http://127.0.0.1:18789/media/ScarFLIX_part-0d465a7414c7c73a/stream.mkv",
          "status_code": 206,
          "bytes_read": 4194304,
          "content_length": "4194304",
          "content_type": "application/octet-stream",
          "accept_ranges": "bytes",
          "elapsed_ms": 3499,
          "reason": "ok"
        }
      },
      "status": "PASS",
      "reason": "webdav_head_and_temporary_range_warm_passed",
      "elapsed_ms": 4712
    },
    {
      "component": "scarflix_v2_streaming_layered_validator",
      "updated_utc": "2026-06-19T04:30:20Z",
      "target_hash": "ScarFLIX_part-a7b67ffdd3c5808a",
      "target_link": "D:\\StremioCatalog\\_Hybrid\\Movies\\_ScarFLIXLive\\06 Discover Movies\\Life of Pi (2012)\\ScarFLIX_part-a7b67ffdd3c5808a",
      "webdav_url": "http://127.0.0.1:18789/media/ScarFLIX_part-a7b67ffdd3c5808a/stream.mkv",
      "map_loaded": true,
      "map_generated_utc": "2026-06-19T04:01:19Z",
      "map_entry_found": true,
      "temporary_buffering": {
        "enabled": true,
        "persisted": false,
        "range_bytes_requested": 4194304
      },
      "layers": {
        "local_symlink_metadata": {
          "status": "PASS",
          "link": "D:\\StremioCatalog\\_Hybrid\\Movies\\_ScarFLIXLive\\06 Discover Movies\\Life of Pi (2012)\\ScarFLIX_part-a7b67ffdd3c5808a",
          "stream_path": "D:\\StremioCatalog\\_Hybrid\\Movies\\_ScarFLIXLive\\06 Discover Movies\\Life of Pi (2012)\\ScarFLIX_part-a7b67ffdd3c5808a",
          "is_symbolic_link": true,
          "link_target": "S:\\media\\ScarFLIX_part-a7b67ffdd3c5808a",
          "error": "",
          "blocking": false,
          "exists": true,
          "is_directory": false,
          "is_file": false
        },
        "webdav_head": {
          "ok": true,
          "method": "HEAD",
          "url": "http://127.0.0.1:18789/media/ScarFLIX_part-a7b67ffdd3c5808a/stream.mkv",
          "status_code": 200,
          "bytes_read": 0,
          "content_length": "2600116885",
          "content_type": "application/octet-stream",
          "accept_ranges": "bytes",
          "elapsed_ms": 1497,
          "attempt": 1,
          "reason": "ok",
          "attempts": 1
        },
        "webdav_head_attempts": [
          {
            "ok": true,
            "method": "HEAD",
            "url": "http://127.0.0.1:18789/media/ScarFLIX_part-a7b67ffdd3c5808a/stream.mkv",
            "status_code": 200,
            "bytes_read": 0,
            "content_length": "2600116885",
            "content_type": "application/octet-stream",
            "accept_ranges": "bytes",
            "elapsed_ms": 1497,
            "attempt": 1,
            "reason": "ok"
          }
        ],
        "webdav_range_warm": {
          "ok": true,
          "method": "GET",
          "url": "http://127.0.0.1:18789/media/ScarFLIX_part-a7b67ffdd3c5808a/stream.mkv",
          "status_code": 206,
          "bytes_read": 4194304,
          "content_length": "4194304",
          "content_type": "application/octet-stream",
          "accept_ranges": "bytes",
          "elapsed_ms": 3524,
          "reason": "ok"
        }
      },
      "status": "PASS",
      "reason": "webdav_head_and_temporary_range_warm_passed",
      "elapsed_ms": 5022
    },
    {
      "component": "scarflix_v2_streaming_layered_validator",
      "updated_utc": "2026-06-19T04:30:28Z",
      "target_hash": "ScarFLIX_part-68e1e99370505860",
      "target_link": "D:\\StremioCatalog\\_Hybrid\\Movies\\_ScarFLIXLive\\06 Discover Movies\\Man on Fire (2004)\\ScarFLIX_part-68e1e99370505860",
      "webdav_url": "http://127.0.0.1:18789/media/ScarFLIX_part-68e1e99370505860/stream.mkv",
      "map_loaded": true,
      "map_generated_utc": "2026-06-19T04:01:19Z",
      "map_entry_found": true,
      "temporary_buffering": {
        "enabled": true,
        "persisted": false,
        "range_bytes_requested": 4194304
      },
      "layers": {
        "local_symlink_metadata": {
          "status": "PASS",
          "link": "D:\\StremioCatalog\\_Hybrid\\Movies\\_ScarFLIXLive\\06 Discover Movies\\Man on Fire (2004)\\ScarFLIX_part-68e1e99370505860",
          "stream_path": "D:\\StremioCatalog\\_Hybrid\\Movies\\_ScarFLIXLive\\06 Discover Movies\\Man on Fire (2004)\\ScarFLIX_part-68e1e99370505860",
          "is_symbolic_link": true,
          "link_target": "S:\\media\\ScarFLIX_part-68e1e99370505860",
          "error": "",
          "blocking": false,
          "exists": true,
          "is_directory": false,
          "is_file": false
        },
        "webdav_head": {
          "ok": true,
          "method": "HEAD",
          "url": "http://127.0.0.1:18789/media/ScarFLIX_part-68e1e99370505860/stream.mkv",
          "status_code": 200,
          "bytes_read": 0,
          "content_length": "1208723832",
          "content_type": "application/octet-stream",
          "accept_ranges": "bytes",
          "elapsed_ms": 1233,
          "attempt": 1,
          "reason": "ok",
          "attempts": 1
        },
        "webdav_head_attempts": [
          {
            "ok": true,
            "method": "HEAD",
            "url": "http://127.0.0.1:18789/media/ScarFLIX_part-68e1e99370505860/stream.mkv",
            "status_code": 200,
            "bytes_read": 0,
            "content_length": "1208723832",
            "content_type": "application/octet-stream",
            "accept_ranges": "bytes",
            "elapsed_ms": 1233,
            "attempt": 1,
            "reason": "ok"
          }
        ],
        "webdav_range_warm": {
          "ok": true,
          "method": "GET",
          "url": "http://127.0.0.1:18789/media/ScarFLIX_part-68e1e99370505860/stream.mkv",
          "status_code": 206,
          "bytes_read": 4194304,
          "content_length": "4194304",
          "content_type": "application/octet-stream",
          "accept_ranges": "bytes",
          "elapsed_ms": 4306,
          "reason": "ok"
        }
      },
      "status": "PASS",
      "reason": "webdav_head_and_temporary_range_warm_passed",
      "elapsed_ms": 5540
    }
  ]
}