{
  "component": "scarflix_v2_streaming_layered_validator",
  "updated_utc": "2026-06-15T04:30:25Z",
  "status": "RUNNING",
  "qa_component": "scarflix_v2_materialized_plex_decision_qa_node",
  "decision_probe_skip": 0,
  "decision_probe_limit": 0,
  "range_bytes": 4194304,
  "summary": {
    "total": 84,
    "passed": 84,
    "review": 0,
    "reasons": {
      "webdav_head_and_temporary_range_warm_passed": 84
    }
  },
  "recent_results": [
    {
      "component": "scarflix_v2_streaming_layered_validator",
      "updated_utc": "2026-06-15T04:27:38Z",
      "target_hash": "ScarFLIX_part-059885f26b12b915",
      "target_link": "D:\\StremioCatalog\\_Hybrid\\Movies\\_ScarFLIXLive\\06 Discover Movies\\Spartacus (1960)\\ScarFLIX_part-059885f26b12b915",
      "webdav_url": "http://127.0.0.1:18789/media/ScarFLIX_part-059885f26b12b915/stream.mkv",
      "map_loaded": true,
      "map_generated_utc": "2026-06-15T04:11:13Z",
      "map_entry_found": true,
      "temporary_buffering": {
        "enabled": true,
        "persisted": false,
        "range_bytes_requested": 4194304
      },
      "layers": {
        "local_symlink_metadata": {
          "status": "PASS",
          "link": "D:\\StremioCatalog\\_Hybrid\\Movies\\_ScarFLIXLive\\06 Discover Movies\\Spartacus (1960)\\ScarFLIX_part-059885f26b12b915",
          "stream_path": "D:\\StremioCatalog\\_Hybrid\\Movies\\_ScarFLIXLive\\06 Discover Movies\\Spartacus (1960)\\ScarFLIX_part-059885f26b12b915",
          "is_symbolic_link": true,
          "link_target": "S:\\media\\ScarFLIX_part-059885f26b12b915",
          "error": "",
          "blocking": false,
          "exists": true,
          "is_directory": false,
          "is_file": false
        },
        "webdav_head": {
          "ok": true,
          "method": "HEAD",
          "url": "http://127.0.0.1:18789/media/ScarFLIX_part-059885f26b12b915/stream.mkv",
          "status_code": 200,
          "bytes_read": 0,
          "content_length": "1627874991",
          "content_type": "application/octet-stream",
          "accept_ranges": "bytes",
          "elapsed_ms": 1326,
          "attempt": 1,
          "reason": "ok",
          "attempts": 1
        },
        "webdav_head_attempts": [
          {
            "ok": true,
            "method": "HEAD",
            "url": "http://127.0.0.1:18789/media/ScarFLIX_part-059885f26b12b915/stream.mkv",
            "status_code": 200,
            "bytes_read": 0,
            "content_length": "1627874991",
            "content_type": "application/octet-stream",
            "accept_ranges": "bytes",
            "elapsed_ms": 1326,
            "attempt": 1,
            "reason": "ok"
          }
        ],
        "webdav_range_warm": {
          "ok": true,
          "method": "GET",
          "url": "http://127.0.0.1:18789/media/ScarFLIX_part-059885f26b12b915/stream.mkv",
          "status_code": 206,
          "bytes_read": 4194304,
          "content_length": "4194304",
          "content_type": "application/octet-stream",
          "accept_ranges": "bytes",
          "elapsed_ms": 3559,
          "reason": "ok"
        }
      },
      "status": "PASS",
      "reason": "webdav_head_and_temporary_range_warm_passed",
      "elapsed_ms": 4887
    },
    {
      "component": "scarflix_v2_streaming_layered_validator",
      "updated_utc": "2026-06-15T04:28:10Z",
      "target_hash": "ScarFLIX_part-fb19346714d96cd7",
      "target_link": "D:\\StremioCatalog\\_Hybrid\\Movies\\_ScarFLIXLive\\06 Discover Movies\\Speed (1994)\\ScarFLIX_part-fb19346714d96cd7",
      "webdav_url": "http://127.0.0.1:18789/media/ScarFLIX_part-fb19346714d96cd7/stream.mkv",
      "map_loaded": true,
      "map_generated_utc": "2026-06-15T04:11:13Z",
      "map_entry_found": true,
      "temporary_buffering": {
        "enabled": true,
        "persisted": false,
        "range_bytes_requested": 4194304
      },
      "layers": {
        "local_symlink_metadata": {
          "status": "PASS",
          "link": "D:\\StremioCatalog\\_Hybrid\\Movies\\_ScarFLIXLive\\06 Discover Movies\\Speed (1994)\\ScarFLIX_part-fb19346714d96cd7",
          "stream_path": "D:\\StremioCatalog\\_Hybrid\\Movies\\_ScarFLIXLive\\06 Discover Movies\\Speed (1994)\\ScarFLIX_part-fb19346714d96cd7",
          "is_symbolic_link": true,
          "link_target": "S:\\media\\ScarFLIX_part-fb19346714d96cd7",
          "error": "",
          "blocking": false,
          "exists": true,
          "is_directory": false,
          "is_file": false
        },
        "webdav_head": {
          "ok": true,
          "method": "HEAD",
          "url": "http://127.0.0.1:18789/media/ScarFLIX_part-fb19346714d96cd7/stream.mkv",
          "status_code": 200,
          "bytes_read": 0,
          "content_length": "787151301",
          "content_type": "application/octet-stream",
          "accept_ranges": "bytes",
          "elapsed_ms": 1445,
          "attempt": 1,
          "reason": "ok",
          "attempts": 1
        },
        "webdav_head_attempts": [
          {
            "ok": true,
            "method": "HEAD",
            "url": "http://127.0.0.1:18789/media/ScarFLIX_part-fb19346714d96cd7/stream.mkv",
            "status_code": 200,
            "bytes_read": 0,
            "content_length": "787151301",
            "content_type": "application/octet-stream",
            "accept_ranges": "bytes",
            "elapsed_ms": 1445,
            "attempt": 1,
            "reason": "ok"
          }
        ],
        "webdav_range_warm": {
          "ok": true,
          "method": "GET",
          "url": "http://127.0.0.1:18789/media/ScarFLIX_part-fb19346714d96cd7/stream.mkv",
          "status_code": 206,
          "bytes_read": 4194304,
          "content_length": "4194304",
          "content_type": "application/octet-stream",
          "accept_ranges": "bytes",
          "elapsed_ms": 3442,
          "reason": "ok"
        }
      },
      "status": "PASS",
      "reason": "webdav_head_and_temporary_range_warm_passed",
      "elapsed_ms": 4888
    },
    {
      "component": "scarflix_v2_streaming_layered_validator",
      "updated_utc": "2026-06-15T04:28:24Z",
      "target_hash": "ScarFLIX_part-9f1e4252bdcbf864",
      "target_link": "D:\\StremioCatalog\\_Hybrid\\Movies\\_ScarFLIXLive\\06 Discover Movies\\Split (2017)\\ScarFLIX_part-9f1e4252bdcbf864",
      "webdav_url": "http://127.0.0.1:18789/media/ScarFLIX_part-9f1e4252bdcbf864/stream.mkv",
      "map_loaded": true,
      "map_generated_utc": "2026-06-15T04:11:13Z",
      "map_entry_found": true,
      "temporary_buffering": {
        "enabled": true,
        "persisted": false,
        "range_bytes_requested": 4194304
      },
      "layers": {
        "local_symlink_metadata": {
          "status": "PASS",
          "link": "D:\\StremioCatalog\\_Hybrid\\Movies\\_ScarFLIXLive\\06 Discover Movies\\Split (2017)\\ScarFLIX_part-9f1e4252bdcbf864",
          "stream_path": "D:\\StremioCatalog\\_Hybrid\\Movies\\_ScarFLIXLive\\06 Discover Movies\\Split (2017)\\ScarFLIX_part-9f1e4252bdcbf864",
          "is_symbolic_link": true,
          "link_target": "S:\\media\\ScarFLIX_part-9f1e4252bdcbf864",
          "error": "",
          "blocking": false,
          "exists": true,
          "is_directory": false,
          "is_file": false
        },
        "webdav_head": {
          "ok": true,
          "method": "HEAD",
          "url": "http://127.0.0.1:18789/media/ScarFLIX_part-9f1e4252bdcbf864/stream.mkv",
          "status_code": 200,
          "bytes_read": 0,
          "content_length": "1841899266",
          "content_type": "application/octet-stream",
          "accept_ranges": "bytes",
          "elapsed_ms": 1389,
          "attempt": 1,
          "reason": "ok",
          "attempts": 1
        },
        "webdav_head_attempts": [
          {
            "ok": true,
            "method": "HEAD",
            "url": "http://127.0.0.1:18789/media/ScarFLIX_part-9f1e4252bdcbf864/stream.mkv",
            "status_code": 200,
            "bytes_read": 0,
            "content_length": "1841899266",
            "content_type": "application/octet-stream",
            "accept_ranges": "bytes",
            "elapsed_ms": 1389,
            "attempt": 1,
            "reason": "ok"
          }
        ],
        "webdav_range_warm": {
          "ok": true,
          "method": "GET",
          "url": "http://127.0.0.1:18789/media/ScarFLIX_part-9f1e4252bdcbf864/stream.mkv",
          "status_code": 206,
          "bytes_read": 4194304,
          "content_length": "4194304",
          "content_type": "application/octet-stream",
          "accept_ranges": "bytes",
          "elapsed_ms": 3398,
          "reason": "ok"
        }
      },
      "status": "PASS",
      "reason": "webdav_head_and_temporary_range_warm_passed",
      "elapsed_ms": 4788
    },
    {
      "component": "scarflix_v2_streaming_layered_validator",
      "updated_utc": "2026-06-15T04:28:41Z",
      "target_hash": "ScarFLIX_part-94620cf0a7e850ab",
      "target_link": "D:\\StremioCatalog\\_Hybrid\\Movies\\_ScarFLIXLive\\06 Discover Movies\\Spy (2015)\\ScarFLIX_part-94620cf0a7e850ab",
      "webdav_url": "http://127.0.0.1:18789/media/ScarFLIX_part-94620cf0a7e850ab/stream.mkv",
      "map_loaded": true,
      "map_generated_utc": "2026-06-15T04:11:13Z",
      "map_entry_found": true,
      "temporary_buffering": {
        "enabled": true,
        "persisted": false,
        "range_bytes_requested": 4194304
      },
      "layers": {
        "local_symlink_metadata": {
          "status": "PASS",
          "link": "D:\\StremioCatalog\\_Hybrid\\Movies\\_ScarFLIXLive\\06 Discover Movies\\Spy (2015)\\ScarFLIX_part-94620cf0a7e850ab",
          "stream_path": "D:\\StremioCatalog\\_Hybrid\\Movies\\_ScarFLIXLive\\06 Discover Movies\\Spy (2015)\\ScarFLIX_part-94620cf0a7e850ab",
          "is_symbolic_link": true,
          "link_target": "S:\\media\\ScarFLIX_part-94620cf0a7e850ab",
          "error": "",
          "blocking": false,
          "exists": true,
          "is_directory": false,
          "is_file": false
        },
        "webdav_head": {
          "ok": true,
          "method": "HEAD",
          "url": "http://127.0.0.1:18789/media/ScarFLIX_part-94620cf0a7e850ab/stream.mkv",
          "status_code": 200,
          "bytes_read": 0,
          "content_length": "4097086324",
          "content_type": "application/octet-stream",
          "accept_ranges": "bytes",
          "elapsed_ms": 1376,
          "attempt": 1,
          "reason": "ok",
          "attempts": 1
        },
        "webdav_head_attempts": [
          {
            "ok": true,
            "method": "HEAD",
            "url": "http://127.0.0.1:18789/media/ScarFLIX_part-94620cf0a7e850ab/stream.mkv",
            "status_code": 200,
            "bytes_read": 0,
            "content_length": "4097086324",
            "content_type": "application/octet-stream",
            "accept_ranges": "bytes",
            "elapsed_ms": 1376,
            "attempt": 1,
            "reason": "ok"
          }
        ],
        "webdav_range_warm": {
          "ok": true,
          "method": "GET",
          "url": "http://127.0.0.1:18789/media/ScarFLIX_part-94620cf0a7e850ab/stream.mkv",
          "status_code": 206,
          "bytes_read": 4194304,
          "content_length": "4194304",
          "content_type": "application/octet-stream",
          "accept_ranges": "bytes",
          "elapsed_ms": 3539,
          "reason": "ok"
        }
      },
      "status": "PASS",
      "reason": "webdav_head_and_temporary_range_warm_passed",
      "elapsed_ms": 4916
    },
    {
      "component": "scarflix_v2_streaming_layered_validator",
      "updated_utc": "2026-06-15T04:28:58Z",
      "target_hash": "ScarFLIX_part-d708c8b30a147319",
      "target_link": "D:\\StremioCatalog\\_Hybrid\\Movies\\_ScarFLIXLive\\06 Discover Movies\\Stand by Me (1986)\\ScarFLIX_part-d708c8b30a147319",
      "webdav_url": "http://127.0.0.1:18789/media/ScarFLIX_part-d708c8b30a147319/stream.mkv",
      "map_loaded": true,
      "map_generated_utc": "2026-06-15T04:11:13Z",
      "map_entry_found": true,
      "temporary_buffering": {
        "enabled": true,
        "persisted": false,
        "range_bytes_requested": 4194304
      },
      "layers": {
        "local_symlink_metadata": {
          "status": "PASS",
          "link": "D:\\StremioCatalog\\_Hybrid\\Movies\\_ScarFLIXLive\\06 Discover Movies\\Stand by Me (1986)\\ScarFLIX_part-d708c8b30a147319",
          "stream_path": "D:\\StremioCatalog\\_Hybrid\\Movies\\_ScarFLIXLive\\06 Discover Movies\\Stand by Me (1986)\\ScarFLIX_part-d708c8b30a147319",
          "is_symbolic_link": true,
          "link_target": "S:\\media\\ScarFLIX_part-d708c8b30a147319",
          "error": "",
          "blocking": false,
          "exists": true,
          "is_directory": false,
          "is_file": false
        },
        "webdav_head": {
          "ok": true,
          "method": "HEAD",
          "url": "http://127.0.0.1:18789/media/ScarFLIX_part-d708c8b30a147319/stream.mkv",
          "status_code": 200,
          "bytes_read": 0,
          "content_length": "3200360934",
          "content_type": "application/octet-stream",
          "accept_ranges": "bytes",
          "elapsed_ms": 1368,
          "attempt": 1,
          "reason": "ok",
          "attempts": 1
        },
        "webdav_head_attempts": [
          {
            "ok": true,
            "method": "HEAD",
            "url": "http://127.0.0.1:18789/media/ScarFLIX_part-d708c8b30a147319/stream.mkv",
            "status_code": 200,
            "bytes_read": 0,
            "content_length": "3200360934",
            "content_type": "application/octet-stream",
            "accept_ranges": "bytes",
            "elapsed_ms": 1368,
            "attempt": 1,
            "reason": "ok"
          }
        ],
        "webdav_range_warm": {
          "ok": true,
          "method": "GET",
          "url": "http://127.0.0.1:18789/media/ScarFLIX_part-d708c8b30a147319/stream.mkv",
          "status_code": 206,
          "bytes_read": 4194304,
          "content_length": "4194304",
          "content_type": "application/octet-stream",
          "accept_ranges": "bytes",
          "elapsed_ms": 3930,
          "reason": "ok"
        }
      },
      "status": "PASS",
      "reason": "webdav_head_and_temporary_range_warm_passed",
      "elapsed_ms": 5299
    },
    {
      "component": "scarflix_v2_streaming_layered_validator",
      "updated_utc": "2026-06-15T04:29:08Z",
      "target_hash": "ScarFLIX_part-6a30d1aa558bac1f",
      "target_link": "D:\\StremioCatalog\\_Hybrid\\Movies\\_ScarFLIXLive\\06 Discover Movies\\Terminator Dark Fate (2019)\\ScarFLIX_part-6a30d1aa558bac1f",
      "webdav_url": "http://127.0.0.1:18789/media/ScarFLIX_part-6a30d1aa558bac1f/stream.mkv",
      "map_loaded": true,
      "map_generated_utc": "2026-06-15T04:11:13Z",
      "map_entry_found": true,
      "temporary_buffering": {
        "enabled": true,
        "persisted": false,
        "range_bytes_requested": 4194304
      },
      "layers": {
        "local_symlink_metadata": {
          "status": "PASS",
          "link": "D:\\StremioCatalog\\_Hybrid\\Movies\\_ScarFLIXLive\\06 Discover Movies\\Terminator Dark Fate (2019)\\ScarFLIX_part-6a30d1aa558bac1f",
          "stream_path": "D:\\StremioCatalog\\_Hybrid\\Movies\\_ScarFLIXLive\\06 Discover Movies\\Terminator Dark Fate (2019)\\ScarFLIX_part-6a30d1aa558bac1f",
          "is_symbolic_link": true,
          "link_target": "S:\\media\\ScarFLIX_part-6a30d1aa558bac1f",
          "error": "",
          "blocking": false,
          "exists": true,
          "is_directory": false,
          "is_file": false
        },
        "webdav_head": {
          "ok": true,
          "method": "HEAD",
          "url": "http://127.0.0.1:18789/media/ScarFLIX_part-6a30d1aa558bac1f/stream.mkv",
          "status_code": 200,
          "bytes_read": 0,
          "content_length": "1661182302",
          "content_type": "application/octet-stream",
          "accept_ranges": "bytes",
          "elapsed_ms": 1486,
          "attempt": 1,
          "reason": "ok",
          "attempts": 1
        },
        "webdav_head_attempts": [
          {
            "ok": true,
            "method": "HEAD",
            "url": "http://127.0.0.1:18789/media/ScarFLIX_part-6a30d1aa558bac1f/stream.mkv",
            "status_code": 200,
            "bytes_read": 0,
            "content_length": "1661182302",
            "content_type": "application/octet-stream",
            "accept_ranges": "bytes",
            "elapsed_ms": 1486,
            "attempt": 1,
            "reason": "ok"
          }
        ],
        "webdav_range_warm": {
          "ok": true,
          "method": "GET",
          "url": "http://127.0.0.1:18789/media/ScarFLIX_part-6a30d1aa558bac1f/stream.mkv",
          "status_code": 206,
          "bytes_read": 4194304,
          "content_length": "4194304",
          "content_type": "application/octet-stream",
          "accept_ranges": "bytes",
          "elapsed_ms": 3745,
          "reason": "ok"
        }
      },
      "status": "PASS",
      "reason": "webdav_head_and_temporary_range_warm_passed",
      "elapsed_ms": 5231
    },
    {
      "component": "scarflix_v2_streaming_layered_validator",
      "updated_utc": "2026-06-15T04:29:23Z",
      "target_hash": "ScarFLIX_part-89731919b552c615",
      "target_link": "D:\\StremioCatalog\\_Hybrid\\Movies\\_ScarFLIXLive\\06 Discover Movies\\Terminator Salvation (2009)\\ScarFLIX_part-89731919b552c615",
      "webdav_url": "http://127.0.0.1:18789/media/ScarFLIX_part-89731919b552c615/stream.mkv",
      "map_loaded": true,
      "map_generated_utc": "2026-06-15T04:11:13Z",
      "map_entry_found": true,
      "temporary_buffering": {
        "enabled": true,
        "persisted": false,
        "range_bytes_requested": 4194304
      },
      "layers": {
        "local_symlink_metadata": {
          "status": "PASS",
          "link": "D:\\StremioCatalog\\_Hybrid\\Movies\\_ScarFLIXLive\\06 Discover Movies\\Terminator Salvation (2009)\\ScarFLIX_part-89731919b552c615",
          "stream_path": "D:\\StremioCatalog\\_Hybrid\\Movies\\_ScarFLIXLive\\06 Discover Movies\\Terminator Salvation (2009)\\ScarFLIX_part-89731919b552c615",
          "is_symbolic_link": true,
          "link_target": "S:\\media\\ScarFLIX_part-89731919b552c615",
          "error": "",
          "blocking": false,
          "exists": true,
          "is_directory": false,
          "is_file": false
        },
        "webdav_head": {
          "ok": true,
          "method": "HEAD",
          "url": "http://127.0.0.1:18789/media/ScarFLIX_part-89731919b552c615/stream.mkv",
          "status_code": 200,
          "bytes_read": 0,
          "content_length": "734893258",
          "content_type": "application/octet-stream",
          "accept_ranges": "bytes",
          "elapsed_ms": 1414,
          "attempt": 1,
          "reason": "ok",
          "attempts": 1
        },
        "webdav_head_attempts": [
          {
            "ok": true,
            "method": "HEAD",
            "url": "http://127.0.0.1:18789/media/ScarFLIX_part-89731919b552c615/stream.mkv",
            "status_code": 200,
            "bytes_read": 0,
            "content_length": "734893258",
            "content_type": "application/octet-stream",
            "accept_ranges": "bytes",
            "elapsed_ms": 1414,
            "attempt": 1,
            "reason": "ok"
          }
        ],
        "webdav_range_warm": {
          "ok": true,
          "method": "GET",
          "url": "http://127.0.0.1:18789/media/ScarFLIX_part-89731919b552c615/stream.mkv",
          "status_code": 206,
          "bytes_read": 4194304,
          "content_length": "4194304",
          "content_type": "application/octet-stream",
          "accept_ranges": "bytes",
          "elapsed_ms": 3498,
          "reason": "ok"
        }
      },
      "status": "PASS",
      "reason": "webdav_head_and_temporary_range_warm_passed",
      "elapsed_ms": 4912
    },
    {
      "component": "scarflix_v2_streaming_layered_validator",
      "updated_utc": "2026-06-15T04:29:55Z",
      "target_hash": "ScarFLIX_part-491a4bfccb102f1e",
      "target_link": "D:\\StremioCatalog\\_Hybrid\\Movies\\_ScarFLIXLive\\06 Discover Movies\\The Big Short (2015)\\ScarFLIX_part-491a4bfccb102f1e",
      "webdav_url": "http://127.0.0.1:18789/media/ScarFLIX_part-491a4bfccb102f1e/stream.mkv",
      "map_loaded": true,
      "map_generated_utc": "2026-06-15T04:11:13Z",
      "map_entry_found": true,
      "temporary_buffering": {
        "enabled": true,
        "persisted": false,
        "range_bytes_requested": 4194304
      },
      "layers": {
        "local_symlink_metadata": {
          "status": "PASS",
          "link": "D:\\StremioCatalog\\_Hybrid\\Movies\\_ScarFLIXLive\\06 Discover Movies\\The Big Short (2015)\\ScarFLIX_part-491a4bfccb102f1e",
          "stream_path": "D:\\StremioCatalog\\_Hybrid\\Movies\\_ScarFLIXLive\\06 Discover Movies\\The Big Short (2015)\\ScarFLIX_part-491a4bfccb102f1e",
          "is_symbolic_link": true,
          "link_target": "S:\\media\\ScarFLIX_part-491a4bfccb102f1e",
          "error": "",
          "blocking": false,
          "exists": true,
          "is_directory": false,
          "is_file": false
        },
        "webdav_head": {
          "ok": true,
          "method": "HEAD",
          "url": "http://127.0.0.1:18789/media/ScarFLIX_part-491a4bfccb102f1e/stream.mkv",
          "status_code": 200,
          "bytes_read": 0,
          "content_length": "3115064244",
          "content_type": "application/octet-stream",
          "accept_ranges": "bytes",
          "elapsed_ms": 1568,
          "attempt": 1,
          "reason": "ok",
          "attempts": 1
        },
        "webdav_head_attempts": [
          {
            "ok": true,
            "method": "HEAD",
            "url": "http://127.0.0.1:18789/media/ScarFLIX_part-491a4bfccb102f1e/stream.mkv",
            "status_code": 200,
            "bytes_read": 0,
            "content_length": "3115064244",
            "content_type": "application/octet-stream",
            "accept_ranges": "bytes",
            "elapsed_ms": 1568,
            "attempt": 1,
            "reason": "ok"
          }
        ],
        "webdav_range_warm": {
          "ok": true,
          "method": "GET",
          "url": "http://127.0.0.1:18789/media/ScarFLIX_part-491a4bfccb102f1e/stream.mkv",
          "status_code": 206,
          "bytes_read": 4194304,
          "content_length": "4194304",
          "content_type": "application/octet-stream",
          "accept_ranges": "bytes",
          "elapsed_ms": 4469,
          "reason": "ok"
        }
      },
      "status": "PASS",
      "reason": "webdav_head_and_temporary_range_warm_passed",
      "elapsed_ms": 6037
    },
    {
      "component": "scarflix_v2_streaming_layered_validator",
      "updated_utc": "2026-06-15T04:30:08Z",
      "target_hash": "ScarFLIX_part-6d4172141ef2dd2a",
      "target_link": "D:\\StremioCatalog\\_Hybrid\\Movies\\_ScarFLIXLive\\06 Discover Movies\\The Boy in the Striped Pyjamas (2008)\\ScarFLIX_part-6d4172141ef2dd2a",
      "webdav_url": "http://127.0.0.1:18789/media/ScarFLIX_part-6d4172141ef2dd2a/stream.mkv",
      "map_loaded": true,
      "map_generated_utc": "2026-06-15T04:11:13Z",
      "map_entry_found": true,
      "temporary_buffering": {
        "enabled": true,
        "persisted": false,
        "range_bytes_requested": 4194304
      },
      "layers": {
        "local_symlink_metadata": {
          "status": "PASS",
          "link": "D:\\StremioCatalog\\_Hybrid\\Movies\\_ScarFLIXLive\\06 Discover Movies\\The Boy in the Striped Pyjamas (2008)\\ScarFLIX_part-6d4172141ef2dd2a",
          "stream_path": "D:\\StremioCatalog\\_Hybrid\\Movies\\_ScarFLIXLive\\06 Discover Movies\\The Boy in the Striped Pyjamas (2008)\\ScarFLIX_part-6d4172141ef2dd2a",
          "is_symbolic_link": true,
          "link_target": "S:\\media\\ScarFLIX_part-6d4172141ef2dd2a",
          "error": "",
          "blocking": false,
          "exists": true,
          "is_directory": false,
          "is_file": false
        },
        "webdav_head": {
          "ok": true,
          "method": "HEAD",
          "url": "http://127.0.0.1:18789/media/ScarFLIX_part-6d4172141ef2dd2a/stream.mkv",
          "status_code": 200,
          "bytes_read": 0,
          "content_length": "1612898414",
          "content_type": "application/octet-stream",
          "accept_ranges": "bytes",
          "elapsed_ms": 1507,
          "attempt": 1,
          "reason": "ok",
          "attempts": 1
        },
        "webdav_head_attempts": [
          {
            "ok": true,
            "method": "HEAD",
            "url": "http://127.0.0.1:18789/media/ScarFLIX_part-6d4172141ef2dd2a/stream.mkv",
            "status_code": 200,
            "bytes_read": 0,
            "content_length": "1612898414",
            "content_type": "application/octet-stream",
            "accept_ranges": "bytes",
            "elapsed_ms": 1507,
            "attempt": 1,
            "reason": "ok"
          }
        ],
        "webdav_range_warm": {
          "ok": true,
          "method": "GET",
          "url": "http://127.0.0.1:18789/media/ScarFLIX_part-6d4172141ef2dd2a/stream.mkv",
          "status_code": 206,
          "bytes_read": 4194304,
          "content_length": "4194304",
          "content_type": "application/octet-stream",
          "accept_ranges": "bytes",
          "elapsed_ms": 3555,
          "reason": "ok"
        }
      },
      "status": "PASS",
      "reason": "webdav_head_and_temporary_range_warm_passed",
      "elapsed_ms": 5062
    },
    {
      "component": "scarflix_v2_streaming_layered_validator",
      "updated_utc": "2026-06-15T04:30:21Z",
      "target_hash": "ScarFLIX_part-1a32188f5276f482",
      "target_link": "D:\\StremioCatalog\\_Hybrid\\Movies\\_ScarFLIXLive\\06 Discover Movies\\The Count of Monte Cristo (2002)\\ScarFLIX_part-1a32188f5276f482",
      "webdav_url": "http://127.0.0.1:18789/media/ScarFLIX_part-1a32188f5276f482/stream.mkv",
      "map_loaded": true,
      "map_generated_utc": "2026-06-15T04:11:13Z",
      "map_entry_found": true,
      "temporary_buffering": {
        "enabled": true,
        "persisted": false,
        "range_bytes_requested": 4194304
      },
      "layers": {
        "local_symlink_metadata": {
          "status": "PASS",
          "link": "D:\\StremioCatalog\\_Hybrid\\Movies\\_ScarFLIXLive\\06 Discover Movies\\The Count of Monte Cristo (2002)\\ScarFLIX_part-1a32188f5276f482",
          "stream_path": "D:\\StremioCatalog\\_Hybrid\\Movies\\_ScarFLIXLive\\06 Discover Movies\\The Count of Monte Cristo (2002)\\ScarFLIX_part-1a32188f5276f482",
          "is_symbolic_link": true,
          "link_target": "S:\\media\\ScarFLIX_part-1a32188f5276f482",
          "error": "",
          "blocking": false,
          "exists": true,
          "is_directory": false,
          "is_file": false
        },
        "webdav_head": {
          "ok": true,
          "method": "HEAD",
          "url": "http://127.0.0.1:18789/media/ScarFLIX_part-1a32188f5276f482/stream.mkv",
          "status_code": 200,
          "bytes_read": 0,
          "content_length": "891238937",
          "content_type": "application/octet-stream",
          "accept_ranges": "bytes",
          "elapsed_ms": 1682,
          "attempt": 1,
          "reason": "ok",
          "attempts": 1
        },
        "webdav_head_attempts": [
          {
            "ok": true,
            "method": "HEAD",
            "url": "http://127.0.0.1:18789/media/ScarFLIX_part-1a32188f5276f482/stream.mkv",
            "status_code": 200,
            "bytes_read": 0,
            "content_length": "891238937",
            "content_type": "application/octet-stream",
            "accept_ranges": "bytes",
            "elapsed_ms": 1682,
            "attempt": 1,
            "reason": "ok"
          }
        ],
        "webdav_range_warm": {
          "ok": true,
          "method": "GET",
          "url": "http://127.0.0.1:18789/media/ScarFLIX_part-1a32188f5276f482/stream.mkv",
          "status_code": 206,
          "bytes_read": 4194304,
          "content_length": "4194304",
          "content_type": "application/octet-stream",
          "accept_ranges": "bytes",
          "elapsed_ms": 3700,
          "reason": "ok"
        }
      },
      "status": "PASS",
      "reason": "webdav_head_and_temporary_range_warm_passed",
      "elapsed_ms": 5382
    }
  ]
}