{
  "component": "jasonos_prime_tv_first_whole_show_private_stage_adapter",
  "schema_version": "jasonos.tv_first.whole_show_private_stage_adapter.v1",
  "updated_utc": "2026-06-18T23:34:18Z",
  "manifest_path": "D:\\PlexTools\\state\\jasonos_prime\\catalogue_expansion\\tv_scope_private_stage_manifests\\spider_noir_220102_private_stage_manifest_20260618T233404Z.prepared.json",
  "private_stage_root": "D:/PlexTools/state/scarflix_v2/tv_first_private_stage",
  "tv_scoped_gate_status": "PASS_TV_SCOPE_MATERIALIZED_QA",
  "prior_private_stage_validator_status": "REVIEW_PRIVATE_STAGE_VALIDATION_PARTIAL",
  "sentinel_status": "PASS",
  "sentinel_alert_level": "LOW",
  "pause_publication_present": true,
  "max_shows": 1,
  "max_episodes": 8,
  "safety": {
    "private_stage_only": true,
    "no_publication_started": true,
    "no_broad_expansion_started": true,
    "no_plex_refresh_performed": true,
    "no_real_debrid_mutation_performed": true,
    "no_webdav_map_write_performed": true,
    "no_path_rewrite_performed": true,
    "no_generic_pending_write": true,
    "no_legacy_direct_resolver_called": true,
    "generic_publisher_not_called": true,
    "source_urls_not_written_to_public_status": true,
    "whole_show_intent": true,
    "current_retry_held_hashes_block_restage": true
  },
  "show_count": 1,
  "episodes_enumerated": 8,
  "already_staged_count": 0,
  "staged_count": 8,
  "review_count": 0,
  "shows": [
    {
      "title": "Spider-Noir",
      "tmdb_id": 220102,
      "seasons_expected": 1,
      "episodes_expected": 8,
      "episodes_enumerated": 8,
      "already_staged_count": 0,
      "staged_count": 8,
      "review_count": 0,
      "episode_manifest_source": "request_episode_targets",
      "error": ""
    }
  ],
  "results_redacted": [
    {
      "title": "Spider-Noir",
      "tmdb_id": 220102,
      "season": 1,
      "episode": 1,
      "status": "PASS_PRIVATE_STAGED_HELD",
      "stage_id": "tv_spider-noir_220102_s01e01_49fcdbf910d5",
      "stream_evidence_redacted": {
        "name": "[RD+] Torrentio\n480p",
        "title_excerpt": "Spider-Noir S01E01 Step Into My Office 480p x264-mSD 👤 203 💾 319.91 MB ⚙️ EZTV",
        "info_hash": "49fcdbf910d58d9cfa4e11f659cb373f9a2f4ca9",
        "url_host": "torrentio.strem.fun",
        "cached_debrid": true,
        "plex_compatible": true,
        "canonical_title_signal": true,
        "season_episode_signal": true,
        "non_english_source_signal": false,
        "selection_mode": "cached_plex_compatible_primary",
        "fallback_requires_private_validation": false,
        "fallback_requires_plex_decision": false,
        "source_url_stored_private_only": true
      }
    },
    {
      "title": "Spider-Noir",
      "tmdb_id": 220102,
      "season": 1,
      "episode": 2,
      "status": "PASS_PRIVATE_STAGED_HELD",
      "stage_id": "tv_spider-noir_220102_s01e02_7c8400a4a02d",
      "stream_evidence_redacted": {
        "name": "[RD+] Torrentio\n480p",
        "title_excerpt": "Spider-Noir S01E02 Tread Lightly 480p x264-mSD 👤 90 💾 276.84 MB ⚙️ EZTV",
        "info_hash": "7c8400a4a02d1b97d8ee355ed7ccbfbc2908d4ae",
        "url_host": "torrentio.strem.fun",
        "cached_debrid": true,
        "plex_compatible": true,
        "canonical_title_signal": true,
        "season_episode_signal": true,
        "non_english_source_signal": false,
        "selection_mode": "cached_plex_compatible_primary",
        "fallback_requires_private_validation": false,
        "fallback_requires_plex_decision": false,
        "source_url_stored_private_only": true
      }
    },
    {
      "title": "Spider-Noir",
      "tmdb_id": 220102,
      "season": 1,
      "episode": 3,
      "status": "PASS_PRIVATE_STAGED_HELD",
      "stage_id": "tv_spider-noir_220102_s01e03_f9bd42f3dd1f",
      "stream_evidence_redacted": {
        "name": "[RD+] Torrentio\n480p",
        "title_excerpt": "Spider-Noir S01E03 Double Cross 480p x264-mSD 👤 115 💾 312.87 MB ⚙️ EZTV",
        "info_hash": "f9bd42f3dd1f44dd9712ed1ab1782f67453c7b4a",
        "url_host": "torrentio.strem.fun",
        "cached_debrid": true,
        "plex_compatible": true,
        "canonical_title_signal": true,
        "season_episode_signal": true,
        "non_english_source_signal": false,
        "selection_mode": "cached_plex_compatible_primary",
        "fallback_requires_private_validation": false,
        "fallback_requires_plex_decision": false,
        "source_url_stored_private_only": true
      }
    },
    {
      "title": "Spider-Noir",
      "tmdb_id": 220102,
      "season": 1,
      "episode": 4,
      "status": "PASS_PRIVATE_STAGED_HELD",
      "stage_id": "tv_spider-noir_220102_s01e04_758769b16d71",
      "stream_evidence_redacted": {
        "name": "[RD+] Torrentio\n480p",
        "title_excerpt": "Spider-Noir S01E04 A Mistake Ill Never Make Again 480p x264-mSD 👤 154 💾 312.18 MB ⚙️ EZTV",
        "info_hash": "758769b16d715000bcdec95c78f78a07ce4ff531",
        "url_host": "torrentio.strem.fun",
        "cached_debrid": true,
        "plex_compatible": true,
        "canonical_title_signal": true,
        "season_episode_signal": true,
        "non_english_source_signal": false,
        "selection_mode": "cached_plex_compatible_primary",
        "fallback_requires_private_validation": false,
        "fallback_requires_plex_decision": false,
        "source_url_stored_private_only": true
      }
    },
    {
      "title": "Spider-Noir",
      "tmdb_id": 220102,
      "season": 1,
      "episode": 5,
      "status": "PASS_PRIVATE_STAGED_HELD",
      "stage_id": "tv_spider-noir_220102_s01e05_337c060019f5",
      "stream_evidence_redacted": {
        "name": "[RD+] Torrentio\n480p",
        "title_excerpt": "Spider-Noir S01E05 Betrayal 480p x264-mSD 👤 89 💾 313.74 MB ⚙️ EZTV",
        "info_hash": "337c060019f55e530b75f13c4e1ed42dd3325529",
        "url_host": "torrentio.strem.fun",
        "cached_debrid": true,
        "plex_compatible": true,
        "canonical_title_signal": true,
        "season_episode_signal": true,
        "non_english_source_signal": false,
        "selection_mode": "cached_plex_compatible_primary",
        "fallback_requires_private_validation": false,
        "fallback_requires_plex_decision": false,
        "source_url_stored_private_only": true
      }
    },
    {
      "title": "Spider-Noir",
      "tmdb_id": 220102,
      "season": 1,
      "episode": 6,
      "status": "PASS_PRIVATE_STAGED_HELD",
      "stage_id": "tv_spider-noir_220102_s01e06_b584ed25005b",
      "stream_evidence_redacted": {
        "name": "[RD+] Torrentio\n480p",
        "title_excerpt": "Spider-Noir S01E06 Nightmare on a Gurney 480p x264-mSD 👤 111 💾 274.65 MB ⚙️ EZTV",
        "info_hash": "b584ed25005b6aadf1b635f09ca8c3ce6c57040d",
        "url_host": "torrentio.strem.fun",
        "cached_debrid": true,
        "plex_compatible": true,
        "canonical_title_signal": true,
        "season_episode_signal": true,
        "non_english_source_signal": false,
        "selection_mode": "cached_plex_compatible_primary",
        "fallback_requires_private_validation": false,
        "fallback_requires_plex_decision": false,
        "source_url_stored_private_only": true
      }
    },
    {
      "title": "Spider-Noir",
      "tmdb_id": 220102,
      "season": 1,
      "episode": 7,
      "status": "PASS_PRIVATE_STAGED_HELD",
      "stage_id": "tv_spider-noir_220102_s01e07_4686ab06431f",
      "stream_evidence_redacted": {
        "name": "[RD+] Torrentio\n480p",
        "title_excerpt": "Spider-Noir S01E07 Nobodys Hero 480p x264-mSD 👤 111 💾 281.35 MB ⚙️ EZTV",
        "info_hash": "4686ab06431facb50dec9c79c05b97124d7f3ad9",
        "url_host": "torrentio.strem.fun",
        "cached_debrid": true,
        "plex_compatible": true,
        "canonical_title_signal": true,
        "season_episode_signal": true,
        "non_english_source_signal": false,
        "selection_mode": "cached_plex_compatible_primary",
        "fallback_requires_private_validation": false,
        "fallback_requires_plex_decision": false,
        "source_url_stored_private_only": true
      }
    },
    {
      "title": "Spider-Noir",
      "tmdb_id": 220102,
      "season": 1,
      "episode": 8,
      "status": "PASS_PRIVATE_STAGED_HELD",
      "stage_id": "tv_spider-noir_220102_s01e08_cb1a9ffb015b",
      "stream_evidence_redacted": {
        "name": "[RD+] Torrentio\n480p",
        "title_excerpt": "Spider-Noir S01E08 The Man in the Mask 480p x264-mSD 👤 100 💾 327.72 MB ⚙️ EZTV",
        "info_hash": "cb1a9ffb015beef8ad4a1b2bf1356a27475fb53e",
        "url_host": "torrentio.strem.fun",
        "cached_debrid": true,
        "plex_compatible": true,
        "canonical_title_signal": true,
        "season_episode_signal": true,
        "non_english_source_signal": false,
        "selection_mode": "cached_plex_compatible_primary",
        "fallback_requires_private_validation": false,
        "fallback_requires_plex_decision": false,
        "source_url_stored_private_only": true
      }
    }
  ],
  "status": "PASS_WHOLE_SHOW_PRIVATE_STAGED",
  "next_safe_action": "Run TV-first private stage validator across the expanded whole-show private stage set, then keep candidates held until a TV-specific publication gate exists and passes."
}
