{
  "component": "scarflix_v2_streaming_layered_validator",
  "updated_utc": "2026-06-14T02:01:22Z",
  "status": "RUNNING",
  "qa_component": "scarflix_v2_materialized_plex_decision_qa_node",
  "decision_probe_skip": 83,
  "decision_probe_limit": 4,
  "range_bytes": 4194304,
  "summary": {
    "total": 3,
    "passed": 2,
    "review": 1,
    "reasons": {
      "webdav_head_and_temporary_range_warm_passed": 2,
      "webdav_head_upstream_server_error": 1
    }
  },
  "recent_results": [
    {
      "component": "scarflix_v2_streaming_layered_validator",
      "updated_utc": "2026-06-14T02:00:50Z",
      "target_hash": "ScarFLIX_part-3ac0e5bd2415a5fc",
      "target_link": "D:\\StremioCatalog\\_Hybrid\\Movies\\_ScarFLIXLive\\06 Discover Movies\\Silent Hill (2006)\\ScarFLIX_part-3ac0e5bd2415a5fc",
      "webdav_url": "http://127.0.0.1:18789/media/ScarFLIX_part-3ac0e5bd2415a5fc/stream.mkv",
      "map_loaded": true,
      "map_generated_utc": "2026-06-09T10:17:48Z",
      "map_entry_found": true,
      "temporary_buffering": {
        "enabled": true,
        "persisted": false,
        "range_bytes_requested": 4194304
      },
      "layers": {
        "local_symlink_metadata": {
          "status": "PASS",
          "link": "D:\\StremioCatalog\\_Hybrid\\Movies\\_ScarFLIXLive\\06 Discover Movies\\Silent Hill (2006)\\ScarFLIX_part-3ac0e5bd2415a5fc",
          "stream_path": "D:\\StremioCatalog\\_Hybrid\\Movies\\_ScarFLIXLive\\06 Discover Movies\\Silent Hill (2006)\\ScarFLIX_part-3ac0e5bd2415a5fc",
          "is_symbolic_link": true,
          "link_target": "S:\\media\\ScarFLIX_part-3ac0e5bd2415a5fc",
          "error": "",
          "blocking": false,
          "exists": true,
          "is_directory": false,
          "is_file": false
        },
        "webdav_head": {
          "ok": true,
          "method": "HEAD",
          "url": "http://127.0.0.1:18789/media/ScarFLIX_part-3ac0e5bd2415a5fc/stream.mkv",
          "status_code": 200,
          "bytes_read": 0,
          "content_length": "1721540280",
          "content_type": "application/octet-stream",
          "accept_ranges": "bytes",
          "elapsed_ms": 1540,
          "attempt": 2,
          "reason": "ok",
          "attempts": 2
        },
        "webdav_head_attempts": [
          {
            "ok": false,
            "method": "HEAD",
            "url": "http://127.0.0.1:18789/media/ScarFLIX_part-3ac0e5bd2415a5fc/stream.mkv",
            "status_code": 0,
            "bytes_read": 0,
            "timed_out": true,
            "error": "timeout",
            "elapsed_ms": 8012,
            "attempt": 1,
            "reason": "timeout"
          },
          {
            "ok": true,
            "method": "HEAD",
            "url": "http://127.0.0.1:18789/media/ScarFLIX_part-3ac0e5bd2415a5fc/stream.mkv",
            "status_code": 200,
            "bytes_read": 0,
            "content_length": "1721540280",
            "content_type": "application/octet-stream",
            "accept_ranges": "bytes",
            "elapsed_ms": 1540,
            "attempt": 2,
            "reason": "ok"
          }
        ],
        "webdav_range_warm": {
          "ok": true,
          "method": "GET",
          "url": "http://127.0.0.1:18789/media/ScarFLIX_part-3ac0e5bd2415a5fc/stream.mkv",
          "status_code": 206,
          "bytes_read": 4194304,
          "content_length": "4194304",
          "content_type": "application/octet-stream",
          "accept_ranges": "bytes",
          "elapsed_ms": 3533,
          "reason": "ok"
        }
      },
      "status": "PASS",
      "reason": "webdav_head_and_temporary_range_warm_passed",
      "elapsed_ms": 13841
    },
    {
      "component": "scarflix_v2_streaming_layered_validator",
      "updated_utc": "2026-06-14T02:01:08Z",
      "target_hash": "ScarFLIX_part-24f719d304fd7aa0",
      "target_link": "D:\\StremioCatalog\\_Hybrid\\Movies\\_ScarFLIXLive\\06 Discover Movies\\Sin Nombre (2009)\\ScarFLIX_part-24f719d304fd7aa0",
      "webdav_url": "http://127.0.0.1:18789/media/ScarFLIX_part-24f719d304fd7aa0/stream.mkv",
      "map_loaded": true,
      "map_generated_utc": "2026-06-09T10:17:48Z",
      "map_entry_found": true,
      "temporary_buffering": {
        "enabled": true,
        "persisted": false,
        "range_bytes_requested": 4194304
      },
      "layers": {
        "local_symlink_metadata": {
          "status": "PASS",
          "link": "D:\\StremioCatalog\\_Hybrid\\Movies\\_ScarFLIXLive\\06 Discover Movies\\Sin Nombre (2009)\\ScarFLIX_part-24f719d304fd7aa0",
          "stream_path": "D:\\StremioCatalog\\_Hybrid\\Movies\\_ScarFLIXLive\\06 Discover Movies\\Sin Nombre (2009)\\ScarFLIX_part-24f719d304fd7aa0",
          "is_symbolic_link": true,
          "link_target": "S:\\media\\ScarFLIX_part-24f719d304fd7aa0",
          "error": "",
          "blocking": false,
          "exists": true,
          "is_directory": false,
          "is_file": false
        },
        "webdav_head": {
          "ok": false,
          "method": "HEAD",
          "url": "http://127.0.0.1:18789/media/ScarFLIX_part-24f719d304fd7aa0/stream.mkv",
          "status_code": 503,
          "bytes_read": 0,
          "content_length": "141",
          "content_type": "text/plain; charset=utf-8",
          "accept_ranges": "bytes",
          "elapsed_ms": 1215,
          "attempt": 2,
          "reason": "upstream_server_error",
          "attempts": 2
        },
        "webdav_head_attempts": [
          {
            "ok": false,
            "method": "HEAD",
            "url": "http://127.0.0.1:18789/media/ScarFLIX_part-24f719d304fd7aa0/stream.mkv",
            "status_code": 503,
            "bytes_read": 0,
            "content_length": "141",
            "content_type": "text/plain; charset=utf-8",
            "accept_ranges": "bytes",
            "elapsed_ms": 4052,
            "attempt": 1,
            "reason": "upstream_server_error"
          },
          {
            "ok": false,
            "method": "HEAD",
            "url": "http://127.0.0.1:18789/media/ScarFLIX_part-24f719d304fd7aa0/stream.mkv",
            "status_code": 503,
            "bytes_read": 0,
            "content_length": "141",
            "content_type": "text/plain; charset=utf-8",
            "accept_ranges": "bytes",
            "elapsed_ms": 1215,
            "attempt": 2,
            "reason": "upstream_server_error"
          }
        ],
        "webdav_head_fallback_range": {
          "ok": false,
          "method": "GET",
          "url": "http://127.0.0.1:18789/media/ScarFLIX_part-24f719d304fd7aa0/stream.mkv",
          "status_code": 503,
          "bytes_read": 141,
          "content_length": "141",
          "content_type": "text/plain; charset=utf-8",
          "accept_ranges": "bytes",
          "elapsed_ms": 832,
          "reason": "upstream_server_error"
        }
      },
      "status": "REVIEW",
      "reason": "webdav_head_upstream_server_error",
      "elapsed_ms": 6868
    },
    {
      "component": "scarflix_v2_streaming_layered_validator",
      "updated_utc": "2026-06-14T02:01:19Z",
      "target_hash": "ScarFLIX_part-ffcfe7a189f19f24",
      "target_link": "D:\\StremioCatalog\\_Hybrid\\Movies\\_ScarFLIXLive\\06 Discover Movies\\Sing (2016)\\ScarFLIX_part-ffcfe7a189f19f24",
      "webdav_url": "http://127.0.0.1:18789/media/ScarFLIX_part-ffcfe7a189f19f24/stream.mkv",
      "map_loaded": true,
      "map_generated_utc": "2026-06-09T10:17:48Z",
      "map_entry_found": true,
      "temporary_buffering": {
        "enabled": true,
        "persisted": false,
        "range_bytes_requested": 4194304
      },
      "layers": {
        "local_symlink_metadata": {
          "status": "PASS",
          "link": "D:\\StremioCatalog\\_Hybrid\\Movies\\_ScarFLIXLive\\06 Discover Movies\\Sing (2016)\\ScarFLIX_part-ffcfe7a189f19f24",
          "stream_path": "D:\\StremioCatalog\\_Hybrid\\Movies\\_ScarFLIXLive\\06 Discover Movies\\Sing (2016)\\ScarFLIX_part-ffcfe7a189f19f24",
          "is_symbolic_link": true,
          "link_target": "S:\\media\\ScarFLIX_part-ffcfe7a189f19f24",
          "error": "",
          "blocking": false,
          "exists": true,
          "is_directory": false,
          "is_file": false
        },
        "webdav_head": {
          "ok": true,
          "method": "HEAD",
          "url": "http://127.0.0.1:18789/media/ScarFLIX_part-ffcfe7a189f19f24/stream.mkv",
          "status_code": 200,
          "bytes_read": 0,
          "content_length": "2918628944",
          "content_type": "application/octet-stream",
          "accept_ranges": "bytes",
          "elapsed_ms": 1644,
          "attempt": 2,
          "reason": "ok",
          "attempts": 2
        },
        "webdav_head_attempts": [
          {
            "ok": false,
            "method": "HEAD",
            "url": "http://127.0.0.1:18789/media/ScarFLIX_part-ffcfe7a189f19f24/stream.mkv",
            "status_code": 0,
            "bytes_read": 0,
            "timed_out": true,
            "error": "timeout",
            "elapsed_ms": 8029,
            "attempt": 1,
            "reason": "timeout"
          },
          {
            "ok": true,
            "method": "HEAD",
            "url": "http://127.0.0.1:18789/media/ScarFLIX_part-ffcfe7a189f19f24/stream.mkv",
            "status_code": 200,
            "bytes_read": 0,
            "content_length": "2918628944",
            "content_type": "application/octet-stream",
            "accept_ranges": "bytes",
            "elapsed_ms": 1644,
            "attempt": 2,
            "reason": "ok"
          }
        ],
        "webdav_range_warm": {
          "ok": true,
          "method": "GET",
          "url": "http://127.0.0.1:18789/media/ScarFLIX_part-ffcfe7a189f19f24/stream.mkv",
          "status_code": 206,
          "bytes_read": 4194304,
          "content_length": "4194304",
          "content_type": "application/octet-stream",
          "accept_ranges": "bytes",
          "elapsed_ms": 3403,
          "reason": "ok"
        }
      },
      "status": "PASS",
      "reason": "webdav_head_and_temporary_range_warm_passed",
      "elapsed_ms": 13840
    }
  ]
}