{
  "component": "jasonos_prime_tv_first_private_stage_validator",
  "schema_version": "jasonos.tv_first.private_stage_validator.v1",
  "updated_utc": "2026-06-19T01:24:00Z",
  "private_stage_root": "D:/PlexTools/state/scarflix_v2/tv_first_private_stage",
  "filters": {
    "stage_prefix": "",
    "tmdb_id": "273240",
    "title_regex": ""
  },
  "safety": {
    "read_only_url_validation": true,
    "no_publication_started": true,
    "no_broad_expansion_started": true,
    "no_plex_refresh_performed": true,
    "no_real_debrid_mutation_performed": true,
    "no_webdav_map_write_performed": true,
    "no_path_rewrite_performed": true,
    "no_generic_pending_write": true,
    "source_urls_not_written_to_public_status": true
  },
  "checked": 8,
  "passed": 8,
  "review": 0,
  "results": [
    {
      "stage_id": "tv_off_campus_273240_s01e01_72c800059222",
      "title": "Off Campus",
      "tmdb_id": 273240,
      "strm_file": "D:\\PlexTools\\state\\scarflix_v2\\tv_first_private_stage\\prepared\\tv_off_campus_273240_s01e01_72c800059222\\Off Campus (2026) - S01E01.strm",
      "status": "PASS_PRIVATE_STAGE_VALIDATED",
      "probe": {
        "ok": true,
        "retryable": false,
        "reason_code": "PASS_PRIVATE_STAGE_URL_VALIDATED",
        "reason": "HEAD and range probes passed.",
        "url_host": "torrentio.strem.fun",
        "head_status": 200,
        "range_status": 206,
        "content_type": "application/force-download",
        "content_length": 440170847,
        "accept_ranges": "bytes",
        "content_range": "bytes 0-1/440170847",
        "source_url_redacted": true,
        "relay_fallback": null
      }
    },
    {
      "stage_id": "tv_off_campus_273240_s01e02_b646fd245621",
      "title": "Off Campus",
      "tmdb_id": 273240,
      "strm_file": "D:\\PlexTools\\state\\scarflix_v2\\tv_first_private_stage\\prepared\\tv_off_campus_273240_s01e02_b646fd245621\\Off Campus (2026) - S01E02.strm",
      "status": "PASS_PRIVATE_STAGE_VALIDATED",
      "probe": {
        "ok": true,
        "retryable": false,
        "reason_code": "PASS_PRIVATE_STAGE_URL_VALIDATED",
        "reason": "HEAD and range probes passed.",
        "url_host": "torrentio.strem.fun",
        "head_status": 200,
        "range_status": 206,
        "content_type": "application/force-download",
        "content_length": 373279598,
        "accept_ranges": "bytes",
        "content_range": "bytes 0-1/373279598",
        "source_url_redacted": true,
        "relay_fallback": null
      }
    },
    {
      "stage_id": "tv_off_campus_273240_s01e03_1b8da2195b2f",
      "title": "Off Campus",
      "tmdb_id": 273240,
      "strm_file": "D:\\PlexTools\\state\\scarflix_v2\\tv_first_private_stage\\prepared\\tv_off_campus_273240_s01e03_1b8da2195b2f\\Off Campus (2026) - S01E03.strm",
      "status": "PASS_PRIVATE_STAGE_VALIDATED",
      "probe": {
        "ok": true,
        "retryable": false,
        "reason_code": "PASS_PRIVATE_STAGE_URL_VALIDATED",
        "reason": "HEAD and range probes passed.",
        "url_host": "torrentio.strem.fun",
        "head_status": 200,
        "range_status": 206,
        "content_type": "application/force-download",
        "content_length": 330086686,
        "accept_ranges": "bytes",
        "content_range": "bytes 0-1/330086686",
        "source_url_redacted": true,
        "relay_fallback": null
      }
    },
    {
      "stage_id": "tv_off_campus_273240_s01e04_3178329be26c",
      "title": "Off Campus",
      "tmdb_id": 273240,
      "strm_file": "D:\\PlexTools\\state\\scarflix_v2\\tv_first_private_stage\\prepared\\tv_off_campus_273240_s01e04_3178329be26c\\Off Campus (2026) - S01E04.strm",
      "status": "PASS_PRIVATE_STAGE_VALIDATED",
      "probe": {
        "ok": true,
        "retryable": false,
        "reason_code": "PASS_PRIVATE_STAGE_URL_VALIDATED",
        "reason": "HEAD and range probes passed.",
        "url_host": "torrentio.strem.fun",
        "head_status": 200,
        "range_status": 206,
        "content_type": "application/force-download",
        "content_length": 372752232,
        "accept_ranges": "bytes",
        "content_range": "bytes 0-1/372752232",
        "source_url_redacted": true,
        "relay_fallback": null
      }
    },
    {
      "stage_id": "tv_off_campus_273240_s01e05_2555dc73ce4d",
      "title": "Off Campus",
      "tmdb_id": 273240,
      "strm_file": "D:\\PlexTools\\state\\scarflix_v2\\tv_first_private_stage\\prepared\\tv_off_campus_273240_s01e05_2555dc73ce4d\\Off Campus (2026) - S01E05.strm",
      "status": "PASS_PRIVATE_STAGE_VALIDATED",
      "probe": {
        "ok": true,
        "retryable": false,
        "reason_code": "PASS_PRIVATE_STAGE_URL_VALIDATED",
        "reason": "HEAD and range probes passed.",
        "url_host": "torrentio.strem.fun",
        "head_status": 200,
        "range_status": 206,
        "content_type": "application/force-download",
        "content_length": 338288488,
        "accept_ranges": "bytes",
        "content_range": "bytes 0-1/338288488",
        "source_url_redacted": true,
        "relay_fallback": null
      }
    },
    {
      "stage_id": "tv_off_campus_273240_s01e06_2e058c3b51cf",
      "title": "Off Campus",
      "tmdb_id": 273240,
      "strm_file": "D:\\PlexTools\\state\\scarflix_v2\\tv_first_private_stage\\prepared\\tv_off_campus_273240_s01e06_2e058c3b51cf\\Off Campus (2026) - S01E06.strm",
      "status": "PASS_PRIVATE_STAGE_VALIDATED",
      "probe": {
        "ok": true,
        "retryable": false,
        "reason_code": "PASS_PRIVATE_STAGE_URL_VALIDATED",
        "reason": "HEAD and range probes passed.",
        "url_host": "torrentio.strem.fun",
        "head_status": 200,
        "range_status": 206,
        "content_type": "application/force-download",
        "content_length": 406750968,
        "accept_ranges": "bytes",
        "content_range": "bytes 0-1/406750968",
        "source_url_redacted": true,
        "relay_fallback": null
      }
    },
    {
      "stage_id": "tv_off_campus_273240_s01e07_1a2b990bc934",
      "title": "Off Campus",
      "tmdb_id": 273240,
      "strm_file": "D:\\PlexTools\\state\\scarflix_v2\\tv_first_private_stage\\prepared\\tv_off_campus_273240_s01e07_1a2b990bc934\\Off Campus (2026) - S01E07.strm",
      "status": "PASS_PRIVATE_STAGE_VALIDATED",
      "probe": {
        "ok": true,
        "retryable": false,
        "reason_code": "PASS_PRIVATE_STAGE_URL_VALIDATED",
        "reason": "HEAD and range probes passed.",
        "url_host": "torrentio.strem.fun",
        "head_status": 200,
        "range_status": 206,
        "content_type": "application/force-download",
        "content_length": 389214577,
        "accept_ranges": "bytes",
        "content_range": "bytes 0-1/389214577",
        "source_url_redacted": true,
        "relay_fallback": null
      }
    },
    {
      "stage_id": "tv_off_campus_273240_s01e08_0226b2f096a7",
      "title": "Off Campus",
      "tmdb_id": 273240,
      "strm_file": "D:\\PlexTools\\state\\scarflix_v2\\tv_first_private_stage\\prepared\\tv_off_campus_273240_s01e08_0226b2f096a7\\Off Campus (2026) - S01E08.strm",
      "status": "PASS_PRIVATE_STAGE_VALIDATED",
      "probe": {
        "ok": true,
        "retryable": false,
        "reason_code": "PASS_PRIVATE_STAGE_URL_VALIDATED",
        "reason": "HEAD and range probes passed.",
        "url_host": "torrentio.strem.fun",
        "head_status": 200,
        "range_status": 206,
        "content_type": "application/force-download",
        "content_length": 385704204,
        "accept_ranges": "bytes",
        "content_range": "bytes 0-1/385704204",
        "source_url_redacted": true,
        "relay_fallback": null
      }
    }
  ],
  "status": "PASS_PRIVATE_STAGE_VALIDATED",
  "next_safe_action": "Proceed to a TV-specific publication gate design for these validated private-stage candidates only."
}
